myqlm_interop-2.0.0.data/scripts/oqasm2circ
myqlm_interop-2.0.0.dist-info/licenses/LICENSE
myqlm_interop-2.0.0.dist-info/licenses/NOTICE
qat/interop/__init__.py
qat/interop/cirq/__init__.py
qat/interop/cirq/converters.py
qat/interop/cirq/providers.py
qat/interop/openqasm/__init__.py
qat/interop/openqasm/oqasm_routine.py
qat/interop/openqasm/qasm_lexer.py
qat/interop/openqasm/qasm_parser.py
qat/interop/projectq/__init__.py
qat/interop/projectq/converters.py
qat/interop/pyquil/__init__.py
qat/interop/pyquil/algorithms.py
qat/interop/pyquil/converters.py
qat/interop/pyquil/providers.py
qat/interop/qiskit/__init__.py
qat/interop/qiskit/converters.py
qat/interop/qiskit/providers.py
qat/interop/qiskit/quantum_channels.py
qat/interop/qiskit/runtime.py
myqlm_interop-2.0.0.dist-info/METADATA
myqlm_interop-2.0.0.dist-info/WHEEL
myqlm_interop-2.0.0.dist-info/top_level.txt
myqlm_interop-2.0.0.dist-info/RECORD
