Metadata-Version: 2.4
Name: myqlm-interop
Version: 2.0.0
Summary: myQLM-interop package
Author: Atos Quantum Lab
License: Atos myQLM EULA
License-File: LICENSE
License-File: NOTICE
Requires-Dist: qat-lang>=2.2.0
Requires-Dist: numpy>=2.0.0
Requires-Dist: ply
Provides-Extra: qiskit-binder
Requires-Dist: qiskit>=1.0.0; python_version >= "3.8" and extra == "qiskit-binder"
Requires-Dist: qiskit-ibm-runtime>=0.11.1; python_version >= "3.8" and extra == "qiskit-binder"
Provides-Extra: projectq-binder
Requires-Dist: projectq>=0.8.0; python_version >= "3.8" and extra == "projectq-binder"
Provides-Extra: cirq-binder
Requires-Dist: cirq>=1.1.0; python_version >= "3.8" and extra == "cirq-binder"
Provides-Extra: pyquil-binder
Requires-Dist: pyquil>=3.5.0; python_version >= "3.8" and extra == "pyquil-binder"
Requires-Dist: quantum-grove>=1.7.0; python_version >= "3.8" and extra == "pyquil-binder"
Provides-Extra: all
Requires-Dist: qiskit>=1.0.0; python_version >= "3.8" and extra == "all"
Requires-Dist: qiskit-ibm-runtime>=0.11.1; python_version >= "3.8" and extra == "all"
Requires-Dist: projectq>=0.8.0; python_version >= "3.8" and extra == "all"
Requires-Dist: cirq>=1.1.0; python_version >= "3.8" and extra == "all"
Requires-Dist: pyquil>=3.5.0; python_version >= "3.8" and extra == "all"
Requires-Dist: quantum-grove>=1.7.0; python_version >= "3.8" and extra == "all"
Dynamic: author
Dynamic: description
Dynamic: license
Dynamic: license-file
Dynamic: provides-extra
Dynamic: requires-dist
Dynamic: summary
